Metadata-Version: 1.0
Name: geograpy
Version: 0.2.5
Summary: Extract countries, regions and cities from a URL or text
Home-page: https://github.com/ushahidi/geograpy
Author: Jonathon Morgan
Author-email: jonathon@ushahidi.com
License: MIT
Download-URL: https://github.com/ushahidi/geograpy/tarball/0.2.5
Platform: UNKNOWN
